odoo/addons/server_environment_iap/README.rst
odoo/addons/server_environment_iap/__init__.py
odoo/addons/server_environment_iap/__manifest__.py
odoo/addons/server_environment_iap/i18n/it.po
odoo/addons/server_environment_iap/i18n/server_environment_iap.pot
odoo/addons/server_environment_iap/models/__init__.py
odoo/addons/server_environment_iap/models/iap_account.py
odoo/addons/server_environment_iap/readme/CONFIGURE.rst
odoo/addons/server_environment_iap/readme/CONTRIBUTORS.rst
odoo/addons/server_environment_iap/readme/DESCRIPTION.rst
odoo/addons/server_environment_iap/readme/ROADMAP.rst
odoo/addons/server_environment_iap/static/description/icon.png
odoo/addons/server_environment_iap/static/description/index.html
odoo/addons/server_environment_iap/tests/__init__.py
odoo/addons/server_environment_iap/tests/config_iap_test.xml
odoo/addons/server_environment_iap/tests/test_server_environment_iap.py
odoo/addons/server_environment_iap/views/iap_views.xml
odoo14_addon_server_environment_iap-14.0.1.0.1.dev7.dist-info/METADATA
odoo14_addon_server_environment_iap-14.0.1.0.1.dev7.dist-info/WHEEL
odoo14_addon_server_environment_iap-14.0.1.0.1.dev7.dist-info/top_level.txt
odoo14_addon_server_environment_iap-14.0.1.0.1.dev7.dist-info/RECORD
